python_docx_symbol/__init__.py
python_docx_symbol/convert.py
python_docx_symbol-0.1.2.dist-info/LICENSE
python_docx_symbol-0.1.2.dist-info/METADATA
python_docx_symbol-0.1.2.dist-info/WHEEL
python_docx_symbol-0.1.2.dist-info/top_level.txt
python_docx_symbol-0.1.2.dist-info/RECORD
